telecoin/__init__.py
telecoin/api.py
telecoin/exceptions.py
telecoin/utils.py
telecoin-0.1.9.dist-info/LICENSE
telecoin-0.1.9.dist-info/WHEEL
telecoin-0.1.9.dist-info/METADATA
telecoin-0.1.9.dist-info/RECORD
